README.rst
setup.py
fh_django_gae_tasks.egg-info/PKG-INFO
fh_django_gae_tasks.egg-info/SOURCES.txt
fh_django_gae_tasks.egg-info/dependency_links.txt
fh_django_gae_tasks.egg-info/requires.txt
fh_django_gae_tasks.egg-info/top_level.txt
gae_tasks/__init__.py
gae_tasks/tasks.py
gae_tasks/urls.py