Metadata-Version: 1.0
Name: fh-django-gae-tasks
Version: 0.2.0
Summary: Django GAE tasks improves upon App Engine's Deferred library and is forked from FreshPlanet's project.
Home-page: https://gitlab.com/futurehaus/django-gae-tasks
Author: UNKNOWN
Author-email: UNKNOWN
License: UNKNOWN
Platform: UNKNOWN
